Metadata-Version: 1.1
Name: pyMKL
Version: 0.0.1
Summary: Python wrapper of Intel MKL routines
Home-page: https://github.com/dwfmarchant/pyMKL
Author: Dave Marchant
Author-email: dwfmarchant@gmail.com
License: MIT
Download-URL: https://github.com/dwfmarchant/pyMKL/tarball/0.0.1
Keywords: sparse linear solver mkl pardiso
Platform: Windows
Platform: Linux
Platform: Solaris
Platform: Mac OS-X
Platform: Unix
Classifier: Development Status :: 3 - Alpha
Classifier: Intended Audience :: Developers
Classifier: Intended Audience :: Science/Research
Classifier: License :: OSI Approved :: MIT License
Classifier: Programming Language :: Python
Classifier: Topic :: Scientific/Engineering
Classifier: Topic :: Scientific/Engineering :: Mathematics
Classifier: Topic :: Scientific/Engineering :: Physics
Classifier: Programming Language :: Python
Classifier: Programming Language :: Python :: 2.7
Classifier: Programming Language :: Python :: 3.3
Classifier: Programming Language :: Python :: 3.4
Classifier: Programming Language :: Python :: 3.5
Classifier: Operating System :: Microsoft :: Windows
Classifier: Operating System :: POSIX
Classifier: Operating System :: Unix
Classifier: Operating System :: MacOS
Classifier: Natural Language :: English
